setup.py
countdb/__init__.py
countdb/aggregators.py
countdb.egg-info/PKG-INFO
countdb.egg-info/SOURCES.txt
countdb.egg-info/dependency_links.txt
countdb.egg-info/top_level.txt
countdb.egg-info/zip-safe
scripts/aggregate
scripts/count