Metadata-Version: 1.1
Name: countdb
Version: 0.5
Summary: count events, store in plain files, aggregate over time
Home-page: https://github.com/netkraken/countdb
Author: Arne Hilmann
Author-email: arne.hilmann@gmail.com
License: UNKNOWN
Platform: UNKNOWN
Classifier: Development Status :: 3 - Alpha
Classifier: Programming Language :: Python
